mechanizeretry/__init__.py
mechanizeretry/mechanizeretry.py
mechanizeretry/timeout.py
mechanizeretry-1.6.dist-info/LICENSE.txt
mechanizeretry-1.6.dist-info/METADATA
mechanizeretry-1.6.dist-info/WHEEL
mechanizeretry-1.6.dist-info/top_level.txt
mechanizeretry-1.6.dist-info/RECORD
