Metadata-Version: 2.1
Name: mechanizeretry
Version: 1.6
Summary: Adds hang protection and retries to mechanize
Home-page: https://github.com/TetrationAnalytics/mechanizeretry
Author: Mike Timm
Author-email: mtimm@tetrationanalytics.com
License: Mike Timm - mtimm@tetrationanalytics.com
Requires-Dist: mechanize
